pixeluxe/__init__.py
pixeluxe/pixeluxe.py
pixeluxe-1.0.dist-info/LICENSE
pixeluxe-1.0.dist-info/METADATA
pixeluxe-1.0.dist-info/WHEEL
pixeluxe-1.0.dist-info/top_level.txt
pixeluxe-1.0.dist-info/RECORD
