Metadata-Version: 2.1
Name: pixeluxe
Version: 1.0
Summary: Library to abstract numpy vectorized array operations for pygame surfaces to mimic shader code
Author-email: Damus666 <macchia.cuordileone@gmail.com>
Project-URL: homepage, https://github.com/Damus666/Pixeluxe
Project-URL: bugtracker, https://github.com/Damus666/Pixeluxe/issues
Classifier: Programming Language :: Python :: 3
Classifier: License :: OSI Approved :: MIT License
Classifier: Operating System :: OS Independent
Requires-Python: >=3.11
License-File: LICENSE
